fast_tabnet/__init__.py
fast_tabnet/_nbdev.py
fast_tabnet/core.py
fast_tabnet-0.2.0.dist-info/LICENSE
fast_tabnet-0.2.0.dist-info/METADATA
fast_tabnet-0.2.0.dist-info/WHEEL
fast_tabnet-0.2.0.dist-info/entry_points.txt
fast_tabnet-0.2.0.dist-info/top_level.txt
fast_tabnet-0.2.0.dist-info/RECORD
