Metadata-Version: 2.1
Name: fast-tabnet
Version: 0.2.0
Summary: TabNet for fastai
Home-page: https://github.com/mgrankin/fast_tabnet/tree/master/
Author: Mikhail Grankin
Author-email: mv.grankin@gmail.com
License: Apache Software License 2.0
Keywords: attention fastai
Platform: UNKNOWN
Classifier: Development Status :: 3 - Alpha
Classifier: Intended Audience :: Developers
Classifier: License :: OSI Approved :: Apache Software License
Classifier: Natural Language :: English
Classifier: Programming Language :: Python :: 3.6
Classifier: Programming Language :: Python :: 3.7
Classifier: Programming Language :: Python :: 3.8
Requires-Python: >=3.6
Requires-Dist: pytorch-tabnet (>=2.0.1)
